cloudconnectlib/__init__.py
cloudconnectlib/client.py
cloudconnectlib/common/__init__.py
cloudconnectlib/common/lib_util.py
cloudconnectlib/common/log.py
cloudconnectlib/common/util.py
cloudconnectlib/configuration/__init__.py
cloudconnectlib/configuration/loader.py
cloudconnectlib/configuration/schema_1_0_0.json
cloudconnectlib/core/__init__.py
cloudconnectlib/core/checkpoint.py
cloudconnectlib/core/defaults.py
cloudconnectlib/core/engine.py
cloudconnectlib/core/engine_v2.py
cloudconnectlib/core/exceptions.py
cloudconnectlib/core/ext.py
cloudconnectlib/core/http.py
cloudconnectlib/core/job.py
cloudconnectlib/core/models.py
cloudconnectlib/core/pipemgr.py
cloudconnectlib/core/plugin.py
cloudconnectlib/core/task.py
cloudconnectlib/core/template.py
cloudconnectlib/splunktacollectorlib/__init__.py
cloudconnectlib/splunktacollectorlib/cloud_connect_mod_input.py
cloudconnectlib/splunktacollectorlib/common/__init__.py
cloudconnectlib/splunktacollectorlib/common/log.py
cloudconnectlib/splunktacollectorlib/common/rwlock.py
cloudconnectlib/splunktacollectorlib/common/schema_meta.py
cloudconnectlib/splunktacollectorlib/config.py
cloudconnectlib/splunktacollectorlib/data_collection/__init__.py
cloudconnectlib/splunktacollectorlib/data_collection/ta_checkpoint_manager.py
cloudconnectlib/splunktacollectorlib/data_collection/ta_config.py
cloudconnectlib/splunktacollectorlib/data_collection/ta_consts.py
cloudconnectlib/splunktacollectorlib/data_collection/ta_data_client.py
cloudconnectlib/splunktacollectorlib/data_collection/ta_data_collector.py
cloudconnectlib/splunktacollectorlib/data_collection/ta_data_loader.py
cloudconnectlib/splunktacollectorlib/data_collection/ta_helper.py
cloudconnectlib/splunktacollectorlib/data_collection/ta_mod_input.py
cloudconnectlib/splunktacollectorlib/splunk_ta_import_declare.py
cloudconnectlib/splunktacollectorlib/ta_cloud_connect_client.py
cloudconnectlib-3.1.2.dist-info/METADATA
cloudconnectlib-3.1.2.dist-info/WHEEL
cloudconnectlib-3.1.2.dist-info/LICENSE
cloudconnectlib-3.1.2.dist-info/RECORD
