Metadata-Version: 2.1
Name: cloudconnectlib
Version: 3.1.2
Summary: APP Cloud Connect
License: Apache-2.0
Author: Addon Factory template
Author-email: addonfactory@splunk.com
Requires-Python: >=3.7,<4.0
Classifier: Intended Audience :: Developers
Classifier: License :: OSI Approved :: Apache Software License
Classifier: Operating System :: OS Independent
Classifier: Programming Language :: Python
Classifier: Programming Language :: Python :: 3
Classifier: Programming Language :: Python :: 3.7
Classifier: Programming Language :: Python :: 3.8
Classifier: Programming Language :: Python :: 3.9
Classifier: Programming Language :: Python :: 3.10
Classifier: Programming Language :: Python :: 3.11
Classifier: Programming Language :: Python :: 3.7
Requires-Dist: PySocks (>=1.7.1,<2.0.0)
Requires-Dist: decorator (==5.1.1)
Requires-Dist: jinja2 (>=2.10.1,<4.0.0)
Requires-Dist: jsonpath-ng (>=1.5.2,<2.0.0)
Requires-Dist: jsonschema (>=4.4.0,<5.0.0)
Requires-Dist: munch (>=2.3.2,<3.0.0)
Requires-Dist: requests (>=2.27.1,<3.0.0)
Requires-Dist: solnlib (>=4.6.0,<5.0.0)
Requires-Dist: splunk-sdk (>=1.6,<2.0)
Requires-Dist: splunktalib (==3.0.0)
Requires-Dist: splunktaucclib (==6.0.0)
